CHANGES.rst
CONTRIBUTORS.rst
LICENSE
MANIFEST.in
README.rst
pyproject.toml
requirements.txt
setup.py
collective/__init__.py
collective.contentrules.setfield.egg-info/PKG-INFO
collective.contentrules.setfield.egg-info/SOURCES.txt
collective.contentrules.setfield.egg-info/dependency_links.txt
collective.contentrules.setfield.egg-info/entry_points.txt
collective.contentrules.setfield.egg-info/namespace_packages.txt
collective.contentrules.setfield.egg-info/not-zip-safe
collective.contentrules.setfield.egg-info/requires.txt
collective.contentrules.setfield.egg-info/top_level.txt
collective/contentrules/__init__.py
collective/contentrules/setfield/__init__.py
collective/contentrules/setfield/action.py
collective/contentrules/setfield/configure.zcml
collective/contentrules/setfield/handlers.py
collective/contentrules/setfield/interfaces.py
collective/contentrules/setfield/restricted.py
collective/contentrules/setfield/testing.py
collective/contentrules/setfield/profiles/tests/contentrules.xml
collective/contentrules/setfield/tests/__init__.py
collective/contentrules/setfield/tests/test_setfield.py