Metadata-Version: 2.1
Name: collective.contentrules.setfield
Version: 0.9.1
Summary: A content rule for setting the value of a field on an object
Home-page: https://github.com/collective/collective.contentrules.setfield
Author: Jon Pentland
Author-email: jon.pentland@pretagov.co.uk
License: GPL Version 2
Keywords: web zope plone contentrules
Platform: UNKNOWN
Classifier: Development Status :: 3 - Alpha
Classifier: Environment :: Web Environment
Classifier: Framework :: Plone
Classifier: Framework :: Plone :: 4.3
Classifier: Framework :: Plone :: 5.0
Classifier: Framework :: Plone :: 5.1
Classifier: Framework :: Zope2
Classifier: Framework :: Zope3
Classifier: Intended Audience :: Developers
Classifier: Intended Audience :: End Users/Desktop
Classifier: Operating System :: OS Independent
Classifier: Programming Language :: Python
Classifier: Programming Language :: Python :: 2.6
Classifier: Programming Language :: Python :: 2.7
Classifier: Topic :: Internet
Classifier: Topic :: Software Development :: Libraries :: Python Modules
Provides-Extra: test
